ascii_builder_z-0.1.4.dist-info/licenses/LICENSE
az/__init__.py
az/ascii_map.py
az/core.py
ascii_builder_z-0.1.4.dist-info/METADATA
ascii_builder_z-0.1.4.dist-info/WHEEL
ascii_builder_z-0.1.4.dist-info/top_level.txt
ascii_builder_z-0.1.4.dist-info/RECORD
