Metadata-Version: 2.4
Name: ascii-builder-z
Version: 0.1.4
Summary: A thick ASCII art generator
Author-email: 3xboiz <ugking2024@gmail.com>
Requires-Python: >=3.7
License-File: LICENSE
Dynamic: license-file
